analytickitanalytics/__init__.py
analytickitanalytics/client.py
analytickitanalytics/consumer.py
analytickitanalytics/feature_flags.py
analytickitanalytics/poller.py
analytickitanalytics/request.py
analytickitanalytics/utils.py
analytickitanalytics/version.py
analytickitanalytics/sentry/__init__.py
analytickitanalytics/sentry/analytickit_integration.py
analytickitanalytics/sentry/django.py
analytickitanalytics/test/__init__.py
analytickitanalytics/test/test_client.py
analytickitanalytics/test/test_consumer.py
analytickitanalytics/test/test_feature_flags.py
analytickitanalytics/test/test_module.py
analytickitanalytics/test/test_request.py
analytickitanalytics/test/test_utils.py
analytickitanalytics-1.0.0.dist-info/LICENSE
analytickitanalytics-1.0.0.dist-info/METADATA
analytickitanalytics-1.0.0.dist-info/WHEEL
analytickitanalytics-1.0.0.dist-info/top_level.txt
analytickitanalytics-1.0.0.dist-info/RECORD
