Metadata-Version: 2.1
Name: analytickitanalytics
Version: 1.0.0
Summary: Integrate AnalyticKit into any python application.
Home-page: https://github.com/analytickit/analytickit-python
Author: Analytickit
Author-email: hey@analytickit.com
Maintainer: AnalyticKit
Maintainer-email: hey@analytickit.com
License: MIT License
Platform: UNKNOWN
Classifier: Development Status :: 5 - Production/Stable
Classifier: Intended Audience :: Developers
Classifier: License :: OSI Approved :: MIT License
Classifier: Operating System :: OS Independent
Classifier: Programming Language :: Python
Classifier: Programming Language :: Python :: 2
Classifier: Programming Language :: Python :: 2.6
Classifier: Programming Language :: Python :: 2.7
Classifier: Programming Language :: Python :: 3
Classifier: Programming Language :: Python :: 3.2
Classifier: Programming Language :: Python :: 3.3
Classifier: Programming Language :: Python :: 3.4
Classifier: Programming Language :: Python :: 3.5
Classifier: Programming Language :: Python :: 3.6
Classifier: Programming Language :: Python :: 3.7
Classifier: Programming Language :: Python :: 3.8
Requires-Dist: requests (<3.0,>=2.7)
Requires-Dist: six (>=1.5)
Requires-Dist: monotonic (>=1.5)
Requires-Dist: backoff (==1.6.0)
Requires-Dist: python-dateutil (>2.1)
Provides-Extra: sentry
Requires-Dist: sentry-sdk ; extra == 'sentry'
Requires-Dist: django ; extra == 'sentry'
